li_api_client/__init__.py
li_api_client/catalogo.py
li_api_client/faturamento.py
li_api_client/integration.py
li_api_client/marketplace.py
li_api_client/pagador.py
li_api_client/pedido.py
li_api_client/plataforma.py
li_api_client/utils.py
li_apiclient-2.2.1.dist-info/DESCRIPTION.rst
li_apiclient-2.2.1.dist-info/METADATA
li_apiclient-2.2.1.dist-info/RECORD
li_apiclient-2.2.1.dist-info/WHEEL
li_apiclient-2.2.1.dist-info/metadata.json
li_apiclient-2.2.1.dist-info/top_level.txt
