Metadata-Version: 2.0
Name: li-apiclient
Version: 2.2.1
Summary: Loja Integrada's API Client
Home-page: https://github.com/lojaintegrada/LI-ApiClient
Author: Loja Integrada
Author-email: contato@lojaintegrada.com.br
License: LIEULA
Platform: UNKNOWN
Classifier: Development Status :: 2 - Pre-Alpha
Classifier: Intended Audience :: Developers
Classifier: License :: OSI Approved :: MIT License
Classifier: Operating System :: OS Independent
Classifier: Programming Language :: Python
Classifier: Programming Language :: Python :: 2.6
Classifier: Programming Language :: Python :: 2.7
Classifier: Topic :: Software Development :: Libraries :: Python Modules
Classifier: Topic :: Internet
Requires-Dist: distribute
